qeh/__init__.py
qeh/__main__.py
qeh/buildingblocks.py
qeh/mos2_test.py
qeh/qeh.py
qeh-23.6.0.dist-info/COPYING.txt
qeh-23.6.0.dist-info/LICENSE
qeh-23.6.0.dist-info/METADATA
qeh-23.6.0.dist-info/WHEEL
qeh-23.6.0.dist-info/entry_points.txt
qeh-23.6.0.dist-info/top_level.txt
qeh-23.6.0.dist-info/RECORD
