Metadata-Version: 2.1
Name: qeh
Version: 23.6.0
Summary: Quantum Electrostatic Heterostructure Model
Home-page: https://gitlab.com/camd/qeh
Author: CAMD
Author-email: mogje@fysik.dtu.dk
Classifier: Development Status :: 2 - Pre-Alpha
Classifier: Environment :: Console
Classifier: License :: OSI Approved :: GNU General Public License v3 or later (GPLv3+)
Classifier: Operating System :: Unix
Classifier: Programming Language :: Python :: 3 :: Only
Classifier: Programming Language :: Python :: 3.6
Classifier: Programming Language :: Python :: 3.7
Classifier: Topic :: Scientific/Engineering :: Physics
License-File: LICENSE
License-File: COPYING.txt
Requires-Dist: ase
Provides-Extra: docs
Requires-Dist: sphinx ; extra == 'docs'
Requires-Dist: sphinxcontrib-programoutput ; extra == 'docs'
